log2py/__init__.py
log2py-1.0.0.dist-info/licenses/LICENSE
log2py-1.0.0.dist-info/METADATA
log2py-1.0.0.dist-info/WHEEL
log2py-1.0.0.dist-info/top_level.txt
log2py-1.0.0.dist-info/RECORD
